{
  "main": {
    "id": "7822195f2079c814",
    "type": "split",
    "children": [
      {
        "id": "e68bcf5249fdf35f",
        "type": "tabs",
        "children": [
          {
            "id": "d32206474e327c30",
            "type": "leaf",
            "state": {
              "type": "markdown",
              "state": {
                "file": "刑法-故意犯罪.md",
                "mode": "source",
                "source": false
              },
              "icon": "lucide-file",
              "title": "刑法-故意犯罪"
            }
          },
          {
            "id": "6ee6dca559383af6",
            "type": "leaf",
            "state": {
              "type": "markdown",
              "state": {
                "file": "09.第06讲：客观要件四：因果关系.md",
                "mode": "source",
                "source": false
              },
              "icon": "lucide-file",
              "title": "09.第06讲：客观要件四：因果关系"
            }
          },
          {
            "id": "b2b3101b94976109",
            "type": "leaf",
            "state": {
              "type": "markdown",
              "state": {
                "file": "10.第07讲：（客观）违法阻却事由（01）.md",
                "mode": "source",
                "source": false
              },
              "icon": "lucide-file",
              "title": "10.第07讲：（客观）违法阻却事由（01）"
            }
          },
          {
            "id": "c38dd041a68653dd",
            "type": "leaf",
            "state": {
              "type": "markdown",
              "state": {
                "file": "刑法-动机错误-不构成强奸罪.md",
                "mode": "source",
                "source": false
              },
              "icon": "lucide-file",
              "title": "刑法-动机错误-不构成强奸罪"
            }
          },
          {
            "id": "bc4692731876ca4f",
            "type": "leaf",
            "state": {
              "type": "markdown",
              "state": {
                "file": "11.第07讲：（客观）违法阻却事由（02）.md",
                "mode": "source",
                "source": false
              },
              "icon": "lucide-file",
              "title": "11.第07讲：（客观）违法阻却事由（02）"
            }
          },
          {
            "id": "e94d2499daf3ac5d",
            "type": "leaf",
            "state": {
              "type": "markdown",
              "state": {
                "file": "12.第08讲：主观要件（01）.md",
                "mode": "source",
                "source": false
              },
              "icon": "lucide-file",
              "title": "12.第08讲：主观要件（01）"
            }
          },
          {
            "id": "3d3f4fa1a20e3988",
            "type": "leaf",
            "state": {
              "type": "markdown",
              "state": {
                "file": "第08个基础概念：危害行为.md",
                "mode": "source",
                "source": false
              },
              "icon": "lucide-file",
              "title": "第08个基础概念：危害行为"
            }
          }
        ],
        "currentTab": 5
      }
    ],
    "direction": "vertical"
  },
  "left": {
    "id": "0723d7b03d91f947",
    "type": "split",
    "children": [
      {
        "id": "21414d1c11bec239",
        "type": "tabs",
        "children": [
          {
            "id": "07ea75003d989534",
            "type": "leaf",
            "state": {
              "type": "file-explorer",
              "state": {
                "sortOrder": "alphabetical",
                "autoReveal": true
              },
              "icon": "lucide-folder-closed",
              "title": "Files"
            }
          },
          {
            "id": "de8970890c666a95",
            "type": "leaf",
            "state": {
              "type": "search",
              "state": {
                "query": "撞死",
                "matchingCase": false,
                "explainSearch": false,
                "collapseAll": false,
                "extraContext": false,
                "sortOrder": "alphabetical"
              },
              "icon": "lucide-search",
              "title": "Search"
            }
          },
          {
            "id": "92593f3a9bac71b5",
            "type": "leaf",
            "state": {
              "type": "bookmarks",
              "state": {},
              "icon": "lucide-bookmark",
              "title": "Bookmarks"
            }
          }
        ]
      }
    ],
    "direction": "horizontal",
    "width": 300
  },
  "right": {
    "id": "2d456175ead85933",
    "type": "split",
    "children": [
      {
        "id": "3c935eaad76d40a8",
        "type": "tabs",
        "children": [
          {
            "id": "267d57a1c7af7258",
            "type": "leaf",
            "state": {
              "type": "backlink",
              "state": {
                "file": "2024私塾民法精讲（第一期：总则+物权）.pdf",
                "collapseAll": false,
                "extraContext": false,
                "sortOrder": "alphabetical",
                "showSearch": false,
                "searchQuery": "",
                "backlinkCollapsed": false,
                "unlinkedCollapsed": true
              },
              "icon": "links-coming-in",
              "title": "Backlinks for 2024私塾民法精讲（第一期：总则+物权）"
            }
          },
          {
            "id": "0400b86c220a97cc",
            "type": "leaf",
            "state": {
              "type": "outgoing-link",
              "state": {
                "file": "2024私塾民法精讲（第一期：总则+物权）.pdf",
                "linksCollapsed": false,
                "unlinkedCollapsed": true
              },
              "icon": "links-going-out",
              "title": "Outgoing links from 2024私塾民法精讲（第一期：总则+物权）"
            }
          },
          {
            "id": "0c26b995d85a014e",
            "type": "leaf",
            "state": {
              "type": "tag",
              "state": {
                "sortOrder": "frequency",
                "useHierarchy": true,
                "showSearch": false,
                "searchQuery": ""
              },
              "icon": "lucide-tags",
              "title": "Tags"
            }
          },
          {
            "id": "9f978239ec052b85",
            "type": "leaf",
            "state": {
              "type": "outline",
              "state": {
                "file": "2024私塾民法精讲（第一期：总则+物权）.pdf",
                "followCursor": false,
                "showSearch": false,
                "searchQuery": ""
              },
              "icon": "lucide-list",
              "title": "Outline of 2024私塾民法精讲（第一期：总则+物权）"
            }
          }
        ]
      }
    ],
    "direction": "horizontal",
    "width": 300,
    "collapsed": true
  },
  "left-ribbon": {
    "hiddenItems": {
      "switcher:Open quick switcher": false,
      "graph:Open graph view": false,
      "canvas:Create new canvas": false,
      "daily-notes:Open today's daily note": false,
      "templates:Insert template": false,
      "command-palette:Open command palette": false
    }
  },
  "active": "e94d2499daf3ac5d",
  "lastOpenFiles": [
    "11.第07讲：（客观）违法阻却事由（02）.md",
    "12.第08讲：主观要件（01）.md",
    "刑法-动机错误-不构成强奸罪.md",
    "10.第07讲：（客观）违法阻却事由（01）.md",
    "刑法-故意犯罪.md",
    "09.第06讲：客观要件四：因果关系.md",
    "第08个基础概念：危害行为.md",
    "第06个基础概念：犯罪构成体系（定罪标准）.md",
    "刑法-强奸罪-只针对活人.md",
    "刑法-强化-08-第五讲.md",
    "刑法-危害行为-实害行为.md",
    "2024私塾民法系统精讲13民法总则.md",
    "刑法-行为与目的存在的原则.md",
    "民法-175题.md",
    "10私塾民法系统精讲1.29.md",
    "282023独角兽法考基础精讲民法-韩祥波.md",
    "2025韩祥波法考民法主客一体精讲课23.md",
    "民法-区分原则.md",
    "532023独角兽法考基础精讲民法-韩祥波.md",
    "522023独角兽法考基础精讲民法-韩祥波.md",
    "512023独角兽法考基础精讲民法-韩祥波.md",
    "502023独角兽法考基础精讲民法-韩祥波.md",
    "492023独角兽法考基础精讲民法-韩祥波.md",
    "482023独角兽法考基础精讲民法-韩祥波.md",
    "472023独角兽法考基础精讲民法-韩祥波.md",
    "462023独角兽法考基础精讲民法-韩祥波.md",
    "【讲义】24法考瑞达刘安琪讲商经知之客观题基础强化(e学专用).pdf",
    "25ZH-真金题-理论法.pdf",
    "25ZH-真金题-行政法 .pdf",
    "2024年系统强化理论法-马峰.pdf",
    "2024年法考基础夯实阶段讲义-行政法-李佳.pdf",
    "2024胡震理论法客观导学讲义_1704548453561.pdf",
    "2024胡震理论法客观导学讲义（1.5）_1704548453561.pdf",
    "2025年法考韩祥波民法精讲(OCR).pdf",
    "2024私塾民法精讲（第一期：总则+物权）.pdf",
    "2024年法考基础夯实阶段讲义-刑法-柏浪涛.pdf",
    "Untitled.canvas"
  ]
}